npTDMS-0.19.0.dist-info/DESCRIPTION.rst
npTDMS-0.19.0.dist-info/METADATA
npTDMS-0.19.0.dist-info/RECORD
npTDMS-0.19.0.dist-info/WHEEL
npTDMS-0.19.0.dist-info/entry_points.txt
npTDMS-0.19.0.dist-info/metadata.json
npTDMS-0.19.0.dist-info/top_level.txt
nptdms/__init__.py
nptdms/common.py
nptdms/daqmx.py
nptdms/log.py
nptdms/scaling.py
nptdms/tdms.py
nptdms/tdms_segment.py
nptdms/tdmsinfo.py
nptdms/types.py
nptdms/utils.py
nptdms/version.py
nptdms/writer.py
nptdms/test/__init__.py
nptdms/test/daqmx_test.py
nptdms/test/pandas_test.py
nptdms/test/scaling_test.py
nptdms/test/tdms_test.py
nptdms/test/test_example_files.py
nptdms/test/types_test.py
nptdms/test/util.py
