Metadata-Version: 2.0
Name: npTDMS
Version: 0.19.0
Summary: Cross-platform, NumPy based module for reading TDMS files produced by LabView.
Home-page: https://github.com/adamreeve/npTDMS
Author: Adam Reeve
Author-email: adreeve@gmail.com
License: LGPL
Platform: UNKNOWN
Classifier: Development Status :: 4 - Beta
Classifier: Operating System :: OS Independent
Classifier: Programming Language :: Python
Classifier: Programming Language :: Python :: 2
Classifier: Programming Language :: Python :: 3
Classifier: Programming Language :: Python :: 2.6
Classifier: Programming Language :: Python :: 2.7
Classifier: Programming Language :: Python :: 3.2
Classifier: Programming Language :: Python :: 3.3
Classifier: Programming Language :: Python :: 3.4
Classifier: Programming Language :: Python :: 3.5
Classifier: Programming Language :: Python :: 3.6
Classifier: Topic :: Scientific/Engineering
Classifier: License :: OSI Approved :: GNU Library or Lesser General Public License (LGPL)
Classifier: Intended Audience :: Science/Research
Classifier: Natural Language :: English
Requires-Dist: numpy
Provides-Extra: hdf
Requires-Dist: h5py; extra == 'hdf'
Provides-Extra: pandas
Requires-Dist: pandas; extra == 'pandas'
Provides-Extra: thermocouple_scaling
Requires-Dist: scipy; extra == 'thermocouple_scaling'
Requires-Dist: thermocouples-reference; extra == 'thermocouple_scaling'
